{
  "answer_get": {
  "DATA": [
  {"timeAIR": "2023-01-23 18:17:39", "timeGROUND": "2023-01-23 18:17:39", "data":
    {"air": [
      {"result": "True", "id": 1, "temperature": 27.85, "humidity": 46.92},
      {"result": "True", "id": 2, "temperature": 29.95, "humidity": 67.55},
      {"result": "True", "id": 3, "temperature": 29.1, "humidity": 72.91},
      {"result": "True", "id": 4, "temperature": 29.28, "humidity": 56.81}
    ],
      "ground": [
        {"result": "True", "id": 1, "humidity": 72.02},
        {"result": "True", "id": 2, "humidity": 62.21},
        {"result": "True", "id": 3, "humidity": 74.5},
        {"result": "True", "id": 4, "humidity": 72.24},
        {"result": "True", "id": 5, "humidity": 70.33},
        {"result": "True", "id": 6, "humidity": 72.16}
      ]}},
  {"timeAIR": "2023-01-23 18:17:43", "timeGROUND": "2023-01-23 18:17:44", "data": {"air": [{"result": "True", "id": 1, "temperature": 27.16, "humidity": 47.93}, {"result": "True", "id": 2, "temperature": 29.9, "humidity": 49.35}, {"result": "True", "id": 3, "temperature": 29.31, "humidity": 60.92}, {"result": "True", "id": 4, "temperature": 29.54, "humidity": 81.54}], "ground": [{"result": "True", "id": 1, "humidity": 65.6}, {"result": "True", "id": 2, "humidity": 64.3}, {"result": "True", "id": 3, "humidity": 71.69}, {"result": "True", "id": 4, "humidity": 68.01}, {"result": "True", "id": 5, "humidity": 70.87}, {"result": "True", "id": 6, "humidity": 70.8}]}}, {"timeAIR": "2023-01-23 18:17:48", "timeGROUND": "2023-01-23 18:17:48", "data": {"air": [{"result": "True", "id": 1, "temperature": 27.21, "humidity": 70.57}, {"result": "True", "id": 2, "temperature": 31.63, "humidity": 43.44}, {"result": "True", "id": 3, "temperature": 30.38, "humidity": 56.67}, {"result": "True", "id": 4, "temperature": 29.3, "humidity": 50.43}], "ground": [{"result": "True", "id": 1, "humidity": 62.22}, {"result": "True", "id": 2, "humidity": 73.58}, {"result": "True", "id": 3, "humidity": 64.16}, {"result": "True", "id": 4, "humidity": 73.88}, {"result": "True", "id": 5, "humidity": 68.94}, {"result": "True", "id": 6, "humidity": 72.57}]}}, {"timeAIR": "2023-01-23 18:17:53", "timeGROUND": "2023-01-23 18:17:53", "data": {"air": [{"result": "True", "id": 1, "temperature": 28.28, "humidity": 51.25}, {"result": "True", "id": 2, "temperature": 28.62, "humidity": 80.65}, {"result": "True", "id": 3, "temperature": 28.63, "humidity": 67.72}, {"result": "True", "id": 4, "temperature": 29.8, "humidity": 64.11}], "ground": [{"result": "True", "id": 1, "humidity": 62.54}, {"result": "True", "id": 2, "humidity": 74.42}, {"result": "True", "id": 3, "humidity": 67.02}, {"result": "True", "id": 4, "humidity": 75.1}, {"result": "True", "id": 5, "humidity": 73.04}, {"result": "True", "id": 6, "humidity": 70.7}]}}, {"timeAIR": "2023-01-23 18:17:57", "timeGROUND": "2023-01-23 18:17:57", "data": {"air": [{"result": "True", "id": 1, "temperature": 32.98, "humidity": 42.82}, {"result": "True", "id": 2, "temperature": 30.12, "humidity": 49.43}, {"result": "True", "id": 3, "temperature": 29.38, "humidity": 48.58}, {"result": "True", "id": 4, "temperature": 29.1, "humidity": 82.99}], "ground": [{"result": "True", "id": 1, "humidity": 62.2}, {"result": "True", "id": 2, "humidity": 66.91}, {"result": "True", "id": 3, "humidity": 70.06}, {"result": "True", "id": 4, "humidity": 64.83}, {"result": "True", "id": 5, "humidity": 73.31}, {"result": "True", "id": 6, "humidity": 70.36}]}}, {"timeAIR": "2023-01-23 18:18:02", "timeGROUND": "2023-01-23 18:18:02", "data": {"air": [{"result": "True", "id": 1, "temperature": 30.13, "humidity": 50.93}, {"result": "True", "id": 2, "temperature": 27.7, "humidity": 46.62}, {"result": "True", "id": 3, "temperature": 28.48, "humidity": 62.15}, {"result": "True", "id": 4, "temperature": 29.4, "humidity": 51.31}], "ground": [{"result": "True", "id": 1, "humidity": 77.52}, {"result": "True", "id": 2, "humidity": 76.73}, {"result": "True", "id": 3, "humidity": 68.87}, {"result": "True", "id": 4, "humidity": 65.83}, {"result": "True", "id": 5, "humidity": 74.84}, {"result": "True", "id": 6, "humidity": 70.53}]}}, {"timeAIR": "2023-01-23 18:18:06", "timeGROUND": "2023-01-23 18:18:06", "data": {"air": [{"result": "True", "id": 1, "temperature": 29.21, "humidity": 43.78}, {"result": "True", "id": 2, "temperature": 29.09, "humidity": 80.03}, {"result": "True", "id": 3, "temperature": 28.13, "humidity": 79.29}, {"result": "True", "id": 4, "temperature": 29.85, "humidity": 75.63}], "ground": [{"result": "True", "id": 1, "humidity": 65.68}, {"result": "True", "id": 2, "humidity": 72.53}, {"result": "True", "id": 3, "humidity": 76.46}, {"result": "True", "id": 4, "humidity": 65.98}, {"result": "True", "id": 5, "humidity": 66.78}, {"result": "True", "id": 6, "humidity": 73.31}]}}, {"timeAIR": "2023-01-23 18:18:11", "timeGROUND": "2023-01-23 18:18:11", "data": {"air": [{"result": "False", "id": 1}, {"result": "True", "id": 2, "temperature": 28.56, "humidity": 70.73}, {"result": "True", "id": 3, "temperature": 30.31, "humidity": 45.91}, {"result": "True", "id": 4, "temperature": 29.96, "humidity": 78.8}], "ground": [{"result": "True", "id": 1, "humidity": 62.4}, {"result": "True", "id": 2, "humidity": 77.44}, {"result": "True", "id": 3, "humidity": 71.86}, {"result": "True", "id": 4, "humidity": 71.43}, {"result": "True", "id": 5, "humidity": 69.63}, {"result": "True", "id": 6, "humidity": 69.75}]}}, {"timeAIR": "2023-01-23 18:18:15", "timeGROUND": "2023-01-23 18:18:15", "data": {"air": [{"result": "True", "id": 1, "temperature": 31.64, "humidity": 63.1}, {"result": "True", "id": 2, "temperature": 30.6, "humidity": 64.13}, {"result": "True", "id": 3, "temperature": 30.44, "humidity": 77.35}, {"result": "False", "id": 4}], "ground": [{"result": "True", "id": 1, "humidity": 67.29}, {"result": "True", "id": 2, "humidity": 69.78}, {"result": "True", "id": 3, "humidity": 69.06}, {"result": "True", "id": 4, "humidity": 64.29}, {"result": "True", "id": 5, "humidity": 73.23}, {"result": "True", "id": 6, "humidity": 67.71}]}}, {"timeAIR": "2023-01-23 18:18:20", "timeGROUND": "2023-01-23 18:18:20", "data": {"air": [{"result": "True", "id": 1, "temperature": 30.27, "humidity": 68.32}, {"result": "True", "id": 2, "temperature": 28.02, "humidity": 45.21}, {"result": "True", "id": 3, "temperature": 28.24, "humidity": 41.62}, {"result": "True", "id": 4, "temperature": 29.08, "humidity": 44.38}], "ground": [{"result": "True", "id": 1, "humidity": 70.92}, {"result": "True", "id": 2, "humidity": 77.02}, {"result": "True", "id": 3, "humidity": 75.7}, {"result": "True", "id": 4, "humidity": 72.77}, {"result": "True", "id": 5, "humidity": 67.62}, {"result": "True", "id": 6, "humidity": 66.84}]}}, {"timeAIR": "2023-01-23 18:18:24", "timeGROUND": "2023-01-23 18:18:25", "data": {"air": [{"result": "True", "id": 1, "temperature": 29.51, "humidity": 46.68}, {"result": "True", "id": 2, "temperature": 27.26, "humidity": 66.68}, {"result": "True", "id": 3, "temperature": 28.19, "humidity": 76.32}, {"result": "True", "id": 4, "temperature": 29.01, "humidity": 61.78}], "ground": [{"result": "True", "id": 1, "humidity": 78.51}, {"result": "True", "id": 2, "humidity": 74.08}, {"result": "True", "id": 3, "humidity": 64.1}, {"result": "True", "id": 4, "humidity": 64.61}, {"result": "True", "id": 5, "humidity": 68.55}, {"result": "True", "id": 6, "humidity": 69.77}]}}, {"timeAIR": "2023-01-23 18:18:29", "timeGROUND": "2023-01-23 18:18:29", "data": {"air": [{"result": "True", "id": 1, "temperature": 31.84, "humidity": 49.23}, {"result": "True", "id": 2, "temperature": 28.12, "humidity": 51.46}, {"result": "True", "id": 3, "temperature": 30.8, "humidity": 63.66}, {"result": "True", "id": 4, "temperature": 29.55, "humidity": 74.5}], "ground": [{"result": "True", "id": 1, "humidity": 71.23}, {"result": "True", "id": 2, "humidity": 71.63}, {"result": "True", "id": 3, "humidity": 63.83}, {"result": "True", "id": 4, "humidity": 74.19}, {"result": "True", "id": 5, "humidity": 70.04}, {"result": "True", "id": 6, "humidity": 67.97}]}}, {"timeAIR": "2023-01-23 18:18:34", "timeGROUND": "2023-01-23 18:18:34", "data": {"air": [{"result": "True", "id": 1, "temperature": 28.33, "humidity": 66.75}, {"result": "True", "id": 2, "temperature": 30.07, "humidity": 72.1}, {"result": "True", "id": 3, "temperature": 30.65, "humidity": 72.77}, {"result": "True", "id": 4, "temperature": 29.46, "humidity": 65.79}], "ground": [{"result": "True", "id": 1, "humidity": 75.94}, {"result": "True", "id": 2, "humidity": 77.56}, {"result": "True", "id": 3, "humidity": 68.42}, {"result": "True", "id": 4, "humidity": 68.01}, {"result": "True", "id": 5, "humidity": 71.98}, {"result": "True", "id": 6, "humidity": 68.07}]}}, {"timeAIR": "2023-01-23 18:18:38", "timeGROUND": "2023-01-23 18:18:39", "data": {"air": [{"result": "True", "id": 1, "temperature": 32.55, "humidity": 74.74}, {"result": "True", "id": 2, "temperature": 27.99, "humidity": 46.57}, {"result": "True", "id": 3, "temperature": 28.22, "humidity": 69.53}, {"result": "True", "id": 4, "temperature": 29.98, "humidity": 60.18}], "ground": [{"result": "True", "id": 1, "humidity": 71.21}, {"result": "True", "id": 2, "humidity": 74.03}, {"result": "True", "id": 3, "humidity": 67.03}, {"result": "True", "id": 4, "humidity": 69.94}, {"result": "True", "id": 5, "humidity": 71.51}, {"result": "True", "id": 6, "humidity": 69.98}]}}, {"timeAIR": "2023-01-23 18:18:43", "timeGROUND": "2023-01-23 18:18:43", "data": {"air": [{"result": "True", "id": 1, "temperature": 29.91, "humidity": 53.68}, {"result": "True", "id": 2, "temperature": 31.69, "humidity": 40.86}, {"result": "True", "id": 3, "temperature": 29.83, "humidity": 75.81}, {"result": "True", "id": 4, "temperature": 29.51, "humidity": 67.91}], "ground": [{"result": "True", "id": 1, "humidity": 65.45}, {"result": "True", "id": 2, "humidity": 70.25}, {"result": "True", "id": 3, "humidity": 65.46}, {"result": "True", "id": 4, "humidity": 64.57}, {"result": "True", "id": 5, "humidity": 65.79}, {"result": "True", "id": 6, "humidity": 67.43}]}}, {"timeAIR": "2023-01-23 18:18:47", "timeGROUND": "2023-01-23 18:18:48", "data": {"air": [{"result": "True", "id": 1, "temperature": 27.39, "humidity": 57.81}, {"result": "True", "id": 2, "temperature": 29.28, "humidity": 52.54}, {"result": "True", "id": 3, "temperature": 28.06, "humidity": 37.68}, {"result": "True", "id": 4, "temperature": 29.87, "humidity": 56.14}], "ground": [{"result": "True", "id": 1, "humidity": 71.46}, {"result": "True", "id": 2, "humidity": 64.9}, {"result": "True", "id": 3, "humidity": 76.29}, {"result": "True", "id": 4, "humidity": 67.88}, {"result": "True", "id": 5, "humidity": 68.74}, {"result": "True", "id": 6, "humidity": 71.0}]}}, {"timeAIR": "2023-01-23 18:18:52", "timeGROUND": "2023-01-23 18:18:52", "data": {"air": [{"result": "True", "id": 1, "temperature": 29.1, "humidity": 55.84}, {"result": "True", "id": 2, "temperature": 30.03, "humidity": 43.68}, {"result": "True", "id": 3, "temperature": 29.37, "humidity": 82.12}, {"result": "True", "id": 4, "temperature": 29.19, "humidity": 62.12}], "ground": [{"result": "True", "id": 1, "humidity": 71.91}, {"result": "True", "id": 2, "humidity": 74.4}, {"result": "True", "id": 3, "humidity": 71.5}, {"result": "True", "id": 4, "humidity": 66.94}, {"result": "False", "id": 5}, {"result": "False", "id": 6}]}}, {"timeAIR": "2023-01-23 18:18:57", "timeGROUND": "2023-01-23 18:18:58", "data": {"air": [{"result": "True", "id": 1, "temperature": 31.12, "humidity": 45.82}, {"result": "True", "id": 2, "temperature": 29.48, "humidity": 70.1}, {"result": "True", "id": 3, "temperature": 29.79, "humidity": 42.63}, {"result": "True", "id": 4, "temperature": 29.44, "humidity": 48.94}], "ground": [{"result": "False", "id": 1}, {"result": "True", "id": 2, "humidity": 72.97}, {"result": "False", "id": 3}, {"result": "True", "id": 4, "humidity": 72.36}, {"result": "False", "id": 5}, {"result": "False", "id": 6}]}}, {"timeAIR": "2023-01-23 18:19:02", "timeGROUND": "2023-01-23 18:19:03", "data": {"air": [{"result": "False", "id": 1}, {"result": "True", "id": 2, "temperature": 30.62, "humidity": 69.01}, {"result": "True", "id": 3, "temperature": 28.33, "humidity": 43.51}, {"result": "True", "id": 4, "temperature": 29.56, "humidity": 79.69}], "ground": [{"result": "True", "id": 1, "humidity": 63.98}, {"result": "True", "id": 2, "humidity": 63.46}, {"result": "True", "id": 3, "humidity": 72.55}, {"result": "True", "id": 4, "humidity": 74.95}, {"result": "True", "id": 5, "humidity": 74.5}, {"result": "False", "id": 6}]}}, {"timeAIR": "2023-01-23 18:19:08", "timeGROUND": "2023-01-23 18:19:08", "data": {"air": [{"result": "True", "id": 1, "temperature": 27.28, "humidity": 65.59}, {"result": "False", "id": 2}, {"result": "True", "id": 3, "temperature": 30.12, "humidity": 37.75}, {"result": "True", "id": 4, "temperature": 30.0, "humidity": 71.67}], "ground": [{"result": "True", "id": 1, "humidity": 61.69}, {"result": "True", "id": 2, "humidity": 63.37}, {"result": "True", "id": 3, "humidity": 70.81}, {"result": "True", "id": 4, "humidity": 75.84}, {"result": "True", "id": 5, "humidity": 65.33}, {"result": "True", "id": 6, "humidity": 72.15}]}}, {"timeAIR": "2023-01-23 18:19:13", "timeGROUND": "2023-01-23 18:19:13", "data": {"air": [{"result": "True", "id": 1, "temperature": 26.08, "humidity": 75.29}, {"result": "True", "id": 2, "temperature": 29.22, "humidity": 67.0}, {"result": "True", "id": 3, "temperature": 30.5, "humidity": 65.23}, {"result": "True", "id": 4, "temperature": 29.6, "humidity": 56.9}], "ground": [{"result": "False", "id": 1}, {"result": "False", "id": 2}, {"result": "True", "id": 3, "humidity": 66.34}, {"result": "True", "id": 4, "humidity": 71.93}, {"result": "False", "id": 5}, {"result": "False", "id": 6}]}}, {"timeAIR": "2023-01-23 18:19:18", "timeGROUND": "2023-01-23 18:19:19", "data": {"air": [{"result": "False", "id": 1}, {"result": "False", "id": 2}, {"result": "False", "id": 3}, {"result": "False", "id": 4}], "ground": [{"result": "False", "id": 1}, {"result": "False", "id": 2}, {"result": "False", "id": 3}, {"result": "False", "id": 4}, {"result": "True", "id": 5, "humidity": 70.93}, {"result": "True", "id": 6, "humidity": 71.99}]}}, {"timeAIR": "2023-01-23 18:19:23", "timeGROUND": "2023-01-23 18:19:23", "data": {"air": [{"result": "True", "id": 1, "temperature": 28.36, "humidity": 76.36}, {"result": "True", "id": 2, "temperature": 28.03, "humidity": 77.34}, {"result": "True", "id": 3, "temperature": 29.32, "humidity": 42.2}, {"result": "True", "id": 4, "temperature": 29.4, "humidity": 42.74}], "ground": [{"result": "True", "id": 1, "humidity": 75.05}, {"result": "True", "id": 2, "humidity": 62.66}, {"result": "True", "id": 3, "humidity": 68.79}, {"result": "False", "id": 4}, {"result": "False", "id": 5}, {"result": "False", "id": 6}]}}, {"timeAIR": "2023-01-23 18:19:27", "timeGROUND": "2023-01-23 18:19:28", "data": {"air": [{"result": "False", "id": 1}, {"result": "False", "id": 2}, {"result": "False", "id": 3}, {"result": "False", "id": 4}], "ground": [{"result": "False", "id": 1}, {"result": "True", "id": 2, "humidity": 68.04}, {"result": "True", "id": 3, "humidity": 64.08}, {"result": "True", "id": 4, "humidity": 74.56}, {"result": "False", "id": 5}, {"result": "False", "id": 6}]}}, {"timeAIR": "2023-01-23 18:19:35", "timeGROUND": "2023-01-23 18:19:39", "data": {"air": [{"result": "False", "id": 1}, {"result": "False", "id": 2}, {"result": "True", "id": 3, "temperature": 29.15, "humidity": 47.79}, {"result": "True", "id": 4, "temperature": 29.79, "humidity": 47.02}], "ground": [{"result": "True", "id": 1, "humidity": 61.91}, {"result": "True", "id": 2, "humidity": 70.95}, {"result": "True", "id": 3, "humidity": 66.81}, {"result": "True", "id": 4, "humidity": 74.54}, {"result": "True", "id": 5, "humidity": 73.22}, {"result": "True", "id": 6, "humidity": 72.8}]}}, {"timeAIR": "2023-01-23 18:19:44", "timeGROUND": "2023-01-23 18:19:44", "data": {"air": [{"result": "False", "id": 1}, {"result": "True", "id": 2, "temperature": 27.16, "humidity": 69.96}, {"result": "False", "id": 3}, {"result": "True", "id": 4, "temperature": 29.94, "humidity": 62.45}], "ground": [{"result": "False", "id": 1}, {"result": "True", "id": 2, "humidity": 72.54}, {"result": "True", "id": 3, "humidity": 73.5}, {"result": "True", "id": 4, "humidity": 68.4}, {"result": "True", "id": 5, "humidity": 67.47}, {"result": "False", "id": 6}]}}, {"timeAIR": "2023-01-23 18:19:48", "timeGROUND": "2023-01-23 18:19:48", "data": {"air": [{"result": "True", "id": 1, "temperature": 32.6, "humidity": 48.78}, {"result": "True", "id": 2, "temperature": 31.79, "humidity": 72.09}, {"result": "True", "id": 3, "temperature": 30.17, "humidity": 79.59}, {"result": "True", "id": 4, "temperature": 29.18, "humidity": 65.55}], "ground": [{"result": "True", "id": 1, "humidity": 77.21}, {"result": "True", "id": 2, "humidity": 75.73}, {"result": "True", "id": 3, "humidity": 76.96}, {"result": "True", "id": 4, "humidity": 70.79}, {"result": "True", "id": 5, "humidity": 71.19}, {"result": "True", "id": 6, "humidity": 68.57}]}}, {"timeAIR": "2023-01-23 18:19:53", "timeGROUND": "2023-01-23 18:19:53", "data": {"air": [{"result": "True", "id": 1, "temperature": 31.81, "humidity": 44.8}, {"result": "True", "id": 2, "temperature": 27.01, "humidity": 58.85}, {"result": "True", "id": 3, "temperature": 29.34, "humidity": 63.74}, {"result": "True", "id": 4, "temperature": 29.1, "humidity": 77.63}], "ground": [{"result": "True", "id": 1, "humidity": 76.31}, {"result": "True", "id": 2, "humidity": 72.97}, {"result": "True", "id": 3, "humidity": 71.68}, {"result": "True", "id": 4, "humidity": 72.82}, {"result": "True", "id": 5, "humidity": 69.42}, {"result": "True", "id": 6, "humidity": 68.44}]}}, {"timeAIR": "2023-01-23 18:19:57", "timeGROUND": "2023-01-23 18:19:58", "data": {"air": [{"result": "True", "id": 1, "temperature": 29.79, "humidity": 79.58}, {"result": "True", "id": 2, "temperature": 28.62, "humidity": 81.69}, {"result": "True", "id": 3, "temperature": 28.87, "humidity": 71.07}, {"result": "True", "id": 4, "temperature": 29.66, "humidity": 68.44}], "ground": [{"result": "True", "id": 1, "humidity": 63.34}, {"result": "True", "id": 2, "humidity": 67.56}, {"result": "True", "id": 3, "humidity": 68.79}, {"result": "True", "id": 4, "humidity": 67.66}, {"result": "True", "id": 5, "humidity": 74.13}, {"result": "True", "id": 6, "humidity": 67.57}]}}, {"timeAIR": "2023-01-23 18:20:02", "timeGROUND": "2023-01-23 18:20:02", "data": {"air": [{"result": "True", "id": 1, "temperature": 31.25, "humidity": 66.47}, {"result": "True", "id": 2, "temperature": 31.58, "humidity": 76.65}, {"result": "True", "id": 3, "temperature": 29.17, "humidity": 49.34}, {"result": "True", "id": 4, "temperature": 29.81, "humidity": 74.78}], "ground": [{"result": "True", "id": 1, "humidity": 66.19}, {"result": "True", "id": 2, "humidity": 76.7}, {"result": "True", "id": 3, "humidity": 75.7}, {"result": "False", "id": 4}, {"result": "False", "id": 5}, {"result": "False", "id": 6}]}}, {"timeAIR": "2023-01-23 18:20:07", "timeGROUND": "2023-01-23 18:20:08", "data": {"air": [{"result": "True", "id": 1, "temperature": 26.02, "humidity": 39.76}, {"result": "True", "id": 2, "temperature": 29.23, "humidity": 71.61}, {"result": "False", "id": 3}, {"result": "False", "id": 4}], "ground": [{"result": "False", "id": 1}, {"result": "False", "id": 2}, {"result": "False", "id": 3}, {"result": "False", "id": 4}, {"result": "True", "id": 5, "humidity": 69.12}, {"result": "False", "id": 6}]}}, {"timeAIR": "2023-01-23 18:20:14", "timeGROUND": "2023-01-23 18:20:14", "data": {"air": [{"result": "True", "id": 1, "temperature": 30.92, "humidity": 46.96}, {"result": "True", "id": 2, "temperature": 30.37, "humidity": 71.76}, {"result": "True", "id": 3, "temperature": 28.39, "humidity": 42.01}, {"result": "True", "id": 4, "temperature": 29.56, "humidity": 74.64}], "ground": [{"result": "True", "id": 1, "humidity": 69.03}, {"result": "True", "id": 2, "humidity": 74.02}, {"result": "False", "id": 3}, {"result": "False", "id": 4}, {"result": "True", "id": 5, "humidity": 67.56}, {"result": "False", "id": 6}]}}, {"timeAIR": "2023-01-23 18:20:19", "timeGROUND": "2023-01-23 18:20:20", "data": {"air": [{"result": "True", "id": 1, "temperature": 29.4, "humidity": 66.88}, {"result": "True", "id": 2, "temperature": 31.82, "humidity": 48.49}, {"result": "False", "id": 3}, {"result": "True", "id": 4, "temperature": 29.35, "humidity": 59.52}], "ground": [{"result": "True", "id": 1, "humidity": 63.66}, {"result": "True", "id": 2, "humidity": 76.94}, {"result": "True", "id": 3, "humidity": 65.9}, {"result": "True", "id": 4, "humidity": 74.79}, {"result": "True", "id": 5, "humidity": 70.6}, {"result": "True", "id": 6, "humidity": 66.13}]}}, {"timeAIR": "2023-01-23 18:20:24", "timeGROUND": "2023-01-23 18:20:25", "data": {"air": [{"result": "True", "id": 1, "temperature": 29.09, "humidity": 68.12}, {"result": "False", "id": 2}, {"result": "True", "id": 3, "temperature": 28.33, "humidity": 60.54}, {"result": "True", "id": 4, "temperature": 29.36, "humidity": 37.65}], "ground": [{"result": "True", "id": 1, "humidity": 71.0}, {"result": "True", "id": 2, "humidity": 71.34}, {"result": "True", "id": 3, "humidity": 71.84}, {"result": "False", "id": 4}, {"result": "False", "id": 5}, {"result": "True", "id": 6, "humidity": 70.52}]}}, {"timeAIR": "2023-01-23 18:20:30", "timeGROUND": "2023-01-23 18:20:32", "data": {"air": [{"result": "True", "id": 1, "temperature": 30.52, "humidity": 66.79}, {"result": "True", "id": 2, "temperature": 29.52, "humidity": 45.26}, {"result": "False", "id": 3}, {"result": "False", "id": 4}], "ground": [{"result": "False", "id": 1}, {"result": "True", "id": 2, "humidity": 67.33}, {"result": "False", "id": 3}, {"result": "True", "id": 4, "humidity": 69.72}, {"result": "True", "id": 5, "humidity": 69.07}, {"result": "False", "id": 6}]}}, {"timeAIR": "2023-01-23 18:20:37", "timeGROUND": "2023-01-23 18:20:37", "data": {"air": [{"result": "False", "id": 1}, {"result": "False", "id": 2}, {"result": "False", "id": 3}, {"result": "True", "id": 4, "temperature": 29.04, "humidity": 79.91}], "ground": [{"result": "True", "id": 1, "humidity": 63.18}, {"result": "True", "id": 2, "humidity": 67.44}, {"result": "False", "id": 3}, {"result": "True", "id": 4, "humidity": 69.33}, {"result": "False", "id": 5}, {"result": "True", "id": 6, "humidity": 70.23}]}}, {"timeAIR": "2023-01-23 18:20:41", "timeGROUND": "2023-01-23 18:20:41", "data": {"air": [{"result": "True", "id": 1, "temperature": 29.28, "humidity": 70.16}, {"result": "True", "id": 2, "temperature": 30.08, "humidity": 38.93}, {"result": "True", "id": 3, "temperature": 30.36, "humidity": 73.08}, {"result": "True", "id": 4, "temperature": 29.17, "humidity": 71.21}], "ground": [{"result": "True", "id": 1, "humidity": 74.4}, {"result": "True", "id": 2, "humidity": 64.22}, {"result": "True", "id": 3, "humidity": 67.23}, {"result": "True", "id": 4, "humidity": 75.51}, {"result": "True", "id": 5, "humidity": 71.57}, {"result": "True", "id": 6, "humidity": 71.04}]}}, {"timeAIR": "2023-01-23 18:20:46", "timeGROUND": "2023-01-23 18:20:46", "data": {"air": [{"result": "True", "id": 1, "temperature": 30.28, "humidity": 65.44}, {"result": "True", "id": 2, "temperature": 31.71, "humidity": 43.69}, {"result": "True", "id": 3, "temperature": 30.96, "humidity": 66.18}, {"result": "True", "id": 4, "temperature": 29.56, "humidity": 41.24}], "ground": [{"result": "True", "id": 1, "humidity": 69.4}, {"result": "True", "id": 2, "humidity": 62.01}, {"result": "True", "id": 3, "humidity": 66.05}, {"result": "True", "id": 4, "humidity": 67.28}, {"result": "True", "id": 5, "humidity": 72.19}, {"result": "False", "id": 6}]}}, {"timeAIR": "2023-01-23 18:20:50", "timeGROUND": "2023-01-23 18:20:51", "data": {"air": [{"result": "True", "id": 1, "temperature": 26.28, "humidity": 77.78}, {"result": "True", "id": 2, "temperature": 31.98, "humidity": 69.59}, {"result": "True", "id": 3, "temperature": 30.91, "humidity": 54.4}, {"result": "True", "id": 4, "temperature": 29.65, "humidity": 44.48}], "ground": [{"result": "True", "id": 1, "humidity": 62.39}, {"result": "True", "id": 2, "humidity": 75.89}, {"result": "True", "id": 3, "humidity": 68.08}, {"result": "True", "id": 4, "humidity": 67.81}, {"result": "True", "id": 5, "humidity": 71.88}, {"result": "True", "id": 6, "humidity": 69.61}]}}, {"timeAIR": "2023-01-23 18:20:55", "timeGROUND": "2023-01-23 18:20:55", "data": {"air": [{"result": "True", "id": 1, "temperature": 27.91, "humidity": 54.13}, {"result": "True", "id": 2, "temperature": 27.77, "humidity": 75.11}, {"result": "True", "id": 3, "temperature": 28.95, "humidity": 41.93}, {"result": "True", "id": 4, "temperature": 29.43, "humidity": 53.38}], "ground": [{"result": "True", "id": 1, "humidity": 77.03}, {"result": "True", "id": 2, "humidity": 65.26}, {"result": "True", "id": 3, "humidity": 73.34}, {"result": "True", "id": 4, "humidity": 64.71}, {"result": "True", "id": 5, "humidity": 72.53}, {"result": "True", "id": 6, "humidity": 67.79}]}}, {"timeAIR": "2023-01-23 18:21:00", "timeGROUND": "2023-01-23 18:21:00", "data": {"air": [{"result": "True", "id": 1, "temperature": 28.76, "humidity": 64.14}, {"result": "True", "id": 2, "temperature": 30.33, "humidity": 43.38}, {"result": "True", "id": 3, "temperature": 29.78, "humidity": 44.5}, {"result": "True", "id": 4, "temperature": 29.59, "humidity": 83.33}], "ground": [{"result": "False", "id": 1}, {"result": "True", "id": 2, "humidity": 66.13}, {"result": "True", "id": 3, "humidity": 64.09}, {"result": "True", "id": 4, "humidity": 64.95}, {"result": "True", "id": 5, "humidity": 65.49}, {"result": "False", "id": 6}]}}, {"timeAIR": "2023-01-23 18:21:04", "timeGROUND": "2023-01-23 18:21:04", "data": {"air": [{"result": "True", "id": 1, "temperature": 30.37, "humidity": 69.21}, {"result": "True", "id": 2, "temperature": 29.1, "humidity": 60.1}, {"result": "True", "id": 3, "temperature": 29.12, "humidity": 71.05}, {"result": "True", "id": 4, "temperature": 29.86, "humidity": 57.98}], "ground": [{"result": "False", "id": 1}, {"result": "True", "id": 2, "humidity": 67.05}, {"result": "True", "id": 3, "humidity": 70.13}, {"result": "False", "id": 4}, {"result": "False", "id": 5}, {"result": "False", "id": 6}]}}, {"timeAIR": "2023-01-23 18:21:09", "timeGROUND": "2023-01-23 18:21:09", "data": {"air": [{"result": "True", "id": 1, "temperature": 27.59, "humidity": 40.45}, {"result": "True", "id": 2, "temperature": 31.78, "humidity": 47.23}, {"result": "True", "id": 3, "temperature": 29.51, "humidity": 50.39}, {"result": "True", "id": 4, "temperature": 29.74, "humidity": 41.35}], "ground": [{"result": "True", "id": 1, "humidity": 78.8}, {"result": "True", "id": 2, "humidity": 65.91}, {"result": "True", "id": 3, "humidity": 66.73}, {"result": "False", "id": 4}, {"result": "False", "id": 5}, {"result": "False", "id": 6}]}}, {"timeAIR": "2023-01-23 18:21:13", "timeGROUND": "2023-01-23 18:21:13", "data": {"air": [{"result": "True", "id": 1, "temperature": 31.62, "humidity": 57.42}, {"result": "True", "id": 2, "temperature": 30.21, "humidity": 60.37}, {"result": "True", "id": 3, "temperature": 30.99, "humidity": 75.2}, {"result": "True", "id": 4, "temperature": 29.33, "humidity": 81.84}], "ground": [{"result": "True", "id": 1, "humidity": 64.0}, {"result": "True", "id": 2, "humidity": 70.86}, {"result": "True", "id": 3, "humidity": 66.1}, {"result": "True", "id": 4, "humidity": 68.63}, {"result": "True", "id": 5, "humidity": 70.73}, {"result": "True", "id": 6, "humidity": 71.71}]}}, {"timeAIR": "2023-01-23 18:21:18", "timeGROUND": "2023-01-23 18:21:18", "data": {"air": [{"result": "True", "id": 1, "temperature": 28.1, "humidity": 71.89}, {"result": "True", "id": 2, "temperature": 29.05, "humidity": 63.05}, {"result": "True", "id": 3, "temperature": 29.76, "humidity": 51.63}, {"result": "True", "id": 4, "temperature": 29.18, "humidity": 69.56}], "ground": [{"result": "True", "id": 1, "humidity": 73.68}, {"result": "True", "id": 2, "humidity": 65.32}, {"result": "True", "id": 3, "humidity": 71.04}, {"result": "True", "id": 4, "humidity": 67.03}, {"result": "True", "id": 5, "humidity": 72.98}, {"result": "True", "id": 6, "humidity": 67.01}]}}, {"timeAIR": "2023-01-23 18:21:22", "timeGROUND": "2023-01-23 18:21:23", "data": {"air": [{"result": "True", "id": 1, "temperature": 32.59, "humidity": 56.74}, {"result": "True", "id": 2, "temperature": 30.05, "humidity": 70.1}, {"result": "True", "id": 3, "temperature": 28.08, "humidity": 70.78}, {"result": "True", "id": 4, "temperature": 29.96, "humidity": 51.1}], "ground": [{"result": "True", "id": 1, "humidity": 72.54}, {"result": "True", "id": 2, "humidity": 64.09}, {"result": "True", "id": 3, "humidity": 76.51}, {"result": "True", "id": 4, "humidity": 69.78}, {"result": "True", "id": 5, "humidity": 66.57}, {"result": "True", "id": 6, "humidity": 68.66}]}}, {"timeAIR": "2023-01-23 18:21:27", "timeGROUND": "2023-01-23 18:21:27", "data": {"air": [{"result": "False", "id": 1}, {"result": "True", "id": 2, "temperature": 29.73, "humidity": 59.46}, {"result": "True", "id": 3, "temperature": 30.77, "humidity": 82.44}, {"result": "True", "id": 4, "temperature": 29.04, "humidity": 65.3}], "ground": [{"result": "True", "id": 1, "humidity": 74.32}, {"result": "True", "id": 2, "humidity": 74.18}, {"result": "True", "id": 3, "humidity": 68.98}, {"result": "True", "id": 4, "humidity": 71.74}, {"result": "True", "id": 5, "humidity": 72.54}, {"result": "True", "id": 6, "humidity": 67.27}]}}, {"timeAIR": "2023-01-23 18:21:32", "timeGROUND": "2023-01-23 18:21:32", "data": {"air": [{"result": "False", "id": 1}, {"result": "False", "id": 2}, {"result": "False", "id": 3}, {"result": "False", "id": 4}], "ground": [{"result": "False", "id": 1}, {"result": "False", "id": 2}, {"result": "False", "id": 3}, {"result": "False", "id": 4}, {"result": "False", "id": 5}, {"result": "False", "id": 6}]}}, {"timeAIR": "2023-01-23 18:21:36", "timeGROUND": "2023-01-23 18:21:37", "data": {"air": [{"result": "True", "id": 1, "temperature": 28.64, "humidity": 74.49}, {"result": "True", "id": 2, "temperature": 30.07, "humidity": 46.06}, {"result": "True", "id": 3, "temperature": 30.12, "humidity": 46.25}, {"result": "True", "id": 4, "temperature": 29.17, "humidity": 46.88}], "ground": [{"result": "True", "id": 1, "humidity": 73.7}, {"result": "True", "id": 2, "humidity": 76.02}, {"result": "True", "id": 3, "humidity": 73.19}, {"result": "True", "id": 4, "humidity": 74.63}, {"result": "True", "id": 5, "humidity": 71.2}, {"result": "True", "id": 6, "humidity": 71.74}]}}, {"timeAIR": "2023-01-23 18:21:41", "timeGROUND": "2023-01-23 18:21:41", "data": {"air": [{"result": "True", "id": 1, "temperature": 27.41, "humidity": 48.32}, {"result": "True", "id": 2, "temperature": 29.45, "humidity": 70.42}, {"result": "True", "id": 3, "temperature": 28.1, "humidity": 73.41}, {"result": "True", "id": 4, "temperature": 29.96, "humidity": 72.21}], "ground": [{"result": "True", "id": 1, "humidity": 74.78}, {"result": "True", "id": 2, "humidity": 62.74}, {"result": "True", "id": 3, "humidity": 69.85}, {"result": "True", "id": 4, "humidity": 73.62}, {"result": "True", "id": 5, "humidity": 72.7}, {"result": "True", "id": 6, "humidity": 67.98}]}}, {"timeAIR": "2023-01-23 18:21:45", "timeGROUND": "2023-01-23 18:21:46", "data": {"air": [{"result": "True", "id": 1, "temperature": 26.91, "humidity": 49.39}, {"result": "True", "id": 2, "temperature": 28.83, "humidity": 78.84}, {"result": "True", "id": 3, "temperature": 30.35, "humidity": 45.09}, {"result": "True", "id": 4, "temperature": 29.06, "humidity": 75.19}], "ground": [{"result": "True", "id": 1, "humidity": 69.97}, {"result": "True", "id": 2, "humidity": 72.98}, {"result": "True", "id": 3, "humidity": 70.63}, {"result": "True", "id": 4, "humidity": 68.76}, {"result": "True", "id": 5, "humidity": 71.46}, {"result": "True", "id": 6, "humidity": 67.67}]}}, {"timeAIR": "2023-01-23 18:21:50", "timeGROUND": "2023-01-23 18:21:50", "data": {"air": [{"result": "True", "id": 1, "temperature": 31.71, "humidity": 49.69}, {"result": "True", "id": 2, "temperature": 30.66, "humidity": 56.74}, {"result": "True", "id": 3, "temperature": 29.6, "humidity": 77.91}, {"result": "True", "id": 4, "temperature": 29.05, "humidity": 48.27}], "ground": [{"result": "True", "id": 1, "humidity": 72.49}, {"result": "True", "id": 2, "humidity": 65.31}, {"result": "True", "id": 3, "humidity": 70.12}, {"result": "True", "id": 4, "humidity": 70.24}, {"result": "True", "id": 5, "humidity": 66.37}, {"result": "True", "id": 6, "humidity": 67.64}]}}, {"timeAIR": "2023-01-23 18:21:55", "timeGROUND": "2023-01-23 18:21:55", "data": {"air": [{"result": "True", "id": 1, "temperature": 31.85, "humidity": 50.96}, {"result": "True", "id": 2, "temperature": 27.46, "humidity": 45.2}, {"result": "True", "id": 3, "temperature": 28.12, "humidity": 43.5}, {"result": "True", "id": 4, "temperature": 29.41, "humidity": 82.25}], "ground": [{"result": "True", "id": 1, "humidity": 75.87}, {"result": "False", "id": 2}, {"result": "True", "id": 3, "humidity": 63.22}, {"result": "True", "id": 4, "humidity": 66.86}, {"result": "False", "id": 5}, {"result": "True", "id": 6, "humidity": 66.64}]}}, {"timeAIR": "2023-01-23 18:21:59", "timeGROUND": "2023-01-23 18:22:00", "data": {"air": [{"result": "True", "id": 1, "temperature": 30.83, "humidity": 48.33}, {"result": "True", "id": 2, "temperature": 27.21, "humidity": 38.23}, {"result": "True", "id": 3, "temperature": 29.84, "humidity": 53.63}, {"result": "True", "id": 4, "temperature": 29.7, "humidity": 42.61}], "ground": [{"result": "True", "id": 1, "humidity": 78.67}, {"result": "True", "id": 2, "humidity": 72.98}, {"result": "True", "id": 3, "humidity": 68.9}, {"result": "True", "id": 4, "humidity": 65.88}, {"result": "True", "id": 5, "humidity": 65.71}, {"result": "True", "id": 6, "humidity": 73.43}]}}, {"timeAIR": "2023-01-23 18:22:04", "timeGROUND": "2023-01-23 18:22:04", "data": {"air": [{"result": "True", "id": 1, "temperature": 28.49, "humidity": 60.65}, {"result": "True", "id": 2, "temperature": 28.81, "humidity": 60.57}, {"result": "True", "id": 3, "temperature": 30.53, "humidity": 39.75}, {"result": "True", "id": 4, "temperature": 29.44, "humidity": 49.69}], "ground": [{"result": "True", "id": 1, "humidity": 68.85}, {"result": "True", "id": 2, "humidity": 66.07}, {"result": "True", "id": 3, "humidity": 76.87}, {"result": "True", "id": 4, "humidity": 75.36}, {"result": "True", "id": 5, "humidity": 68.22}, {"result": "True", "id": 6, "humidity": 70.78}]}}, {"timeAIR": "2023-01-23 18:22:09", "timeGROUND": "2023-01-23 18:22:09", "data": {"air": [{"result": "True", "id": 1, "temperature": 28.05, "humidity": 75.33}, {"result": "True", "id": 2, "temperature": 29.68, "humidity": 49.74}, {"result": "True", "id": 3, "temperature": 28.73, "humidity": 42.48}, {"result": "True", "id": 4, "temperature": 29.54, "humidity": 54.41}], "ground": [{"result": "True", "id": 1, "humidity": 75.5}, {"result": "True", "id": 2, "humidity": 76.19}, {"result": "True", "id": 3, "humidity": 71.62}, {"result": "True", "id": 4, "humidity": 75.45}, {"result": "True", "id": 5, "humidity": 73.25}, {"result": "True", "id": 6, "humidity": 69.47}]}}, {"timeAIR": "2023-01-23 18:22:13", "timeGROUND": "2023-01-23 18:22:13", "data": {"air": [{"result": "True", "id": 1, "temperature": 26.86, "humidity": 63.58}, {"result": "True", "id": 2, "temperature": 27.46, "humidity": 81.52}, {"result": "True", "id": 3, "temperature": 30.42, "humidity": 55.25}, {"result": "True", "id": 4, "temperature": 29.98, "humidity": 47.72}], "ground": [{"result": "True", "id": 1, "humidity": 73.4}, {"result": "True", "id": 2, "humidity": 70.17}, {"result": "True", "id": 3, "humidity": 73.88}, {"result": "True", "id": 4, "humidity": 64.68}, {"result": "True", "id": 5, "humidity": 69.45}, {"result": "True", "id": 6, "humidity": 72.07}]}}, {"timeAIR": "2023-01-23 18:22:18", "timeGROUND": "2023-01-23 18:22:18", "data": {"air": [{"result": "False", "id": 1}, {"result": "True", "id": 2, "temperature": 28.93, "humidity": 80.29}, {"result": "True", "id": 3, "temperature": 29.33, "humidity": 68.62}, {"result": "True", "id": 4, "temperature": 29.55, "humidity": 78.04}], "ground": [{"result": "True", "id": 1, "humidity": 64.8}, {"result": "True", "id": 2, "humidity": 75.68}, {"result": "True", "id": 3, "humidity": 64.11}, {"result": "True", "id": 4, "humidity": 75.94}, {"result": "True", "id": 5, "humidity": 67.72}, {"result": "True", "id": 6, "humidity": 66.79}]}}, {"timeAIR": "2023-01-23 18:22:23", "timeGROUND": "2023-01-23 18:22:23", "data": {"air": [{"result": "True", "id": 1, "temperature": 28.97, "humidity": 64.54}, {"result": "True", "id": 2, "temperature": 27.83, "humidity": 48.03}, {"result": "False", "id": 3}, {"result": "False", "id": 4}], "ground": [{"result": "True", "id": 1, "humidity": 78.16}, {"result": "True", "id": 2, "humidity": 70.05}, {"result": "True", "id": 3, "humidity": 64.11}, {"result": "True", "id": 4, "humidity": 67.23}, {"result": "True", "id": 5, "humidity": 68.0}, {"result": "True", "id": 6, "humidity": 69.28}]}}, {"timeAIR": "2023-01-23 18:22:27", "timeGROUND": "2023-01-23 18:22:28", "data": {"air": [{"result": "True", "id": 1, "temperature": 27.56, "humidity": 47.23}, {"result": "True", "id": 2, "temperature": 31.79, "humidity": 66.93}, {"result": "True", "id": 3, "temperature": 30.7, "humidity": 45.78}, {"result": "True", "id": 4, "temperature": 29.92, "humidity": 76.14}], "ground": [{"result": "True", "id": 1, "humidity": 77.72}, {"result": "True", "id": 2, "humidity": 75.02}, {"result": "True", "id": 3, "humidity": 64.53}, {"result": "True", "id": 4, "humidity": 64.99}, {"result": "True", "id": 5, "humidity": 71.25}, {"result": "True", "id": 6, "humidity": 72.75}]}}, {"timeAIR": "2023-01-23 18:22:32", "timeGROUND": "2023-01-23 18:22:32", "data": {"air": [{"result": "True", "id": 1, "temperature": 32.51, "humidity": 51.35}, {"result": "True", "id": 2, "temperature": 28.38, "humidity": 74.14}, {"result": "True", "id": 3, "temperature": 29.59, "humidity": 41.25}, {"result": "True", "id": 4, "temperature": 29.05, "humidity": 63.95}], "ground": [{"result": "True", "id": 1, "humidity": 77.71}, {"result": "True", "id": 2, "humidity": 74.01}, {"result": "True", "id": 3, "humidity": 74.76}, {"result": "True", "id": 4, "humidity": 69.58}, {"result": "True", "id": 5, "humidity": 71.17}, {"result": "True", "id": 6, "humidity": 72.76}]}}, {"timeAIR": "2023-01-23 18:22:37", "timeGROUND": "2023-01-23 18:22:37", "data": {"air": [{"result": "True", "id": 1, "temperature": 30.92, "humidity": 63.35}, {"result": "True", "id": 2, "temperature": 30.08, "humidity": 75.51}, {"result": "True", "id": 3, "temperature": 29.85, "humidity": 51.96}, {"result": "True", "id": 4, "temperature": 29.17, "humidity": 63.67}], "ground": [{"result": "True", "id": 1, "humidity": 73.91}, {"result": "True", "id": 2, "humidity": 74.86}, {"result": "True", "id": 3, "humidity": 71.6}, {"result": "True", "id": 4, "humidity": 65.85}, {"result": "True", "id": 5, "humidity": 69.14}, {"result": "True", "id": 6, "humidity": 71.08}]}}, {"timeAIR": "2023-01-23 18:22:41", "timeGROUND": "2023-01-23 18:22:41", "data": {"air": [{"result": "True", "id": 1, "temperature": 32.0, "humidity": 67.63}, {"result": "True", "id": 2, "temperature": 30.02, "humidity": 44.68}, {"result": "True", "id": 3, "temperature": 28.41, "humidity": 60.33}, {"result": "False", "id": 4}], "ground": [{"result": "True", "id": 1, "humidity": 74.43}, {"result": "True", "id": 2, "humidity": 74.22}, {"result": "True", "id": 3, "humidity": 71.03}, {"result": "True", "id": 4, "humidity": 68.45}, {"result": "True", "id": 5, "humidity": 71.08}, {"result": "True", "id": 6, "humidity": 69.15}]}}, {"timeAIR": "2023-01-23 18:22:46", "timeGROUND": "2023-01-23 18:22:46", "data": {"air": [{"result": "True", "id": 1, "temperature": 30.32, "humidity": 61.89}, {"result": "True", "id": 2, "temperature": 31.05, "humidity": 69.06}, {"result": "True", "id": 3, "temperature": 29.48, "humidity": 57.61}, {"result": "True", "id": 4, "temperature": 29.61, "humidity": 45.33}], "ground": [{"result": "True", "id": 1, "humidity": 61.98}, {"result": "True", "id": 2, "humidity": 65.77}, {"result": "True", "id": 3, "humidity": 70.74}, {"result": "True", "id": 4, "humidity": 69.17}, {"result": "True", "id": 5, "humidity": 73.16}, {"result": "True", "id": 6, "humidity": 69.28}]}}, {"timeAIR": "2023-01-23 18:22:50", "timeGROUND": "2023-01-23 18:22:51", "data": {"air": [{"result": "True", "id": 1, "temperature": 26.95, "humidity": 47.87}, {"result": "True", "id": 2, "temperature": 30.34, "humidity": 65.61}, {"result": "True", "id": 3, "temperature": 28.65, "humidity": 73.71}, {"result": "True", "id": 4, "temperature": 29.13, "humidity": 49.82}], "ground": [{"result": "True", "id": 1, "humidity": 67.28}, {"result": "True", "id": 2, "humidity": 77.41}, {"result": "True", "id": 3, "humidity": 75.05}, {"result": "True", "id": 4, "humidity": 68.46}, {"result": "True", "id": 5, "humidity": 65.9}, {"result": "True", "id": 6, "humidity": 66.95}]}}, {"timeAIR": "2023-01-23 18:22:55", "timeGROUND": "2023-01-23 18:22:55", "data": {"air": [{"result": "True", "id": 1, "temperature": 27.92, "humidity": 51.84}, {"result": "True", "id": 2, "temperature": 30.44, "humidity": 56.26}, {"result": "True", "id": 3, "temperature": 30.4, "humidity": 73.91}, {"result": "True", "id": 4, "temperature": 29.51, "humidity": 64.67}], "ground": [{"result": "True", "id": 1, "humidity": 73.75}, {"result": "True", "id": 2, "humidity": 65.32}, {"result": "True", "id": 3, "humidity": 75.88}, {"result": "True", "id": 4, "humidity": 67.54}, {"result": "True", "id": 5, "humidity": 65.49}, {"result": "True", "id": 6, "humidity": 73.82}]}}, {"timeAIR": "2023-01-23 18:23:00", "timeGROUND": "2023-01-23 18:23:00", "data": {"air": [{"result": "True", "id": 1, "temperature": 31.09, "humidity": 47.75}, {"result": "True", "id": 2, "temperature": 27.1, "humidity": 50.77}, {"result": "True", "id": 3, "temperature": 29.92, "humidity": 48.33}, {"result": "True", "id": 4, "temperature": 29.43, "humidity": 41.54}], "ground": [{"result": "True", "id": 1, "humidity": 72.24}, {"result": "True", "id": 2, "humidity": 67.0}, {"result": "True", "id": 3, "humidity": 70.74}, {"result": "True", "id": 4, "humidity": 67.03}, {"result": "True", "id": 5, "humidity": 70.59}, {"result": "True", "id": 6, "humidity": 66.66}]}}, {"timeAIR": "2023-01-23 18:23:04", "timeGROUND": "2023-01-23 18:23:04", "data": {"air": [{"result": "True", "id": 1, "temperature": 32.01, "humidity": 61.39}, {"result": "True", "id": 2, "temperature": 28.79, "humidity": 74.63}, {"result": "True", "id": 3, "temperature": 29.62, "humidity": 41.19}, {"result": "True", "id": 4, "temperature": 29.31, "humidity": 74.63}], "ground": [{"result": "True", "id": 1, "humidity": 78.37}, {"result": "True", "id": 2, "humidity": 69.49}, {"result": "True", "id": 3, "humidity": 67.02}, {"result": "True", "id": 4, "humidity": 74.91}, {"result": "True", "id": 5, "humidity": 70.04}, {"result": "True", "id": 6, "humidity": 73.11}]}}, {"timeAIR": "2023-01-23 18:23:09", "timeGROUND": "2023-01-23 18:23:09", "data": {"air": [{"result": "True", "id": 1, "temperature": 29.87, "humidity": 46.93}, {"result": "True", "id": 2, "temperature": 30.2, "humidity": 49.65}, {"result": "True", "id": 3, "temperature": 30.56, "humidity": 51.67}, {"result": "True", "id": 4, "temperature": 29.32, "humidity": 73.71}], "ground": [{"result": "True", "id": 1, "humidity": 69.92}, {"result": "True", "id": 2, "humidity": 76.79}, {"result": "True", "id": 3, "humidity": 76.08}, {"result": "True", "id": 4, "humidity": 69.38}, {"result": "True", "id": 5, "humidity": 65.86}, {"result": "True", "id": 6, "humidity": 70.22}]}}, {"timeAIR": "2023-01-23 18:23:13", "timeGROUND": "2023-01-23 18:23:14", "data": {"air": [{"result": "True", "id": 1, "temperature": 29.63, "humidity": 77.5}, {"result": "True", "id": 2, "temperature": 29.71, "humidity": 58.21}, {"result": "True", "id": 3, "temperature": 29.69, "humidity": 51.67}, {"result": "True", "id": 4, "temperature": 29.39, "humidity": 48.28}], "ground": [{"result": "True", "id": 1, "humidity": 72.13}, {"result": "True", "id": 2, "humidity": 74.13}, {"result": "True", "id": 3, "humidity": 74.53}, {"result": "True", "id": 4, "humidity": 69.82}, {"result": "True", "id": 5, "humidity": 73.82}, {"result": "True", "id": 6, "humidity": 70.91}]}}, {"timeAIR": "2023-01-23 18:23:18", "timeGROUND": "2023-01-23 18:23:18", "data": {"air": [{"result": "True", "id": 1, "temperature": 26.75, "humidity": 40.98}, {"result": "True", "id": 2, "temperature": 30.37, "humidity": 60.68}, {"result": "True", "id": 3, "temperature": 29.19, "humidity": 75.18}, {"result": "True", "id": 4, "temperature": 29.82, "humidity": 51.98}], "ground": [{"result": "True", "id": 1, "humidity": 78.15}, {"result": "True", "id": 2, "humidity": 74.64}, {"result": "True", "id": 3, "humidity": 65.15}, {"result": "True", "id": 4, "humidity": 64.38}, {"result": "True", "id": 5, "humidity": 65.1}, {"result": "True", "id": 6, "humidity": 66.95}]}}, {"timeAIR": "2023-01-23 18:23:23", "timeGROUND": "2023-01-23 18:23:23", "data": {"air": [{"result": "True", "id": 1, "temperature": 27.39, "humidity": 45.45}, {"result": "True", "id": 2, "temperature": 30.13, "humidity": 45.72}, {"result": "True", "id": 3, "temperature": 29.08, "humidity": 38.16}, {"result": "True", "id": 4, "temperature": 29.78, "humidity": 63.21}], "ground": [{"result": "False", "id": 1}, {"result": "False", "id": 2}, {"result": "True", "id": 3, "humidity": 68.54}, {"result": "True", "id": 4, "humidity": 65.7}, {"result": "True", "id": 5, "humidity": 67.77}, {"result": "True", "id": 6, "humidity": 73.66}]}}, {"timeAIR": "2023-01-23 18:23:27", "timeGROUND": "2023-01-23 18:23:28", "data": {"air": [{"result": "True", "id": 1, "temperature": 26.19, "humidity": 67.75}, {"result": "True", "id": 2, "temperature": 30.11, "humidity": 61.48}, {"result": "True", "id": 3, "temperature": 28.32, "humidity": 54.59}, {"result": "True", "id": 4, "temperature": 29.24, "humidity": 49.16}], "ground": [{"result": "True", "id": 1, "humidity": 62.78}, {"result": "True", "id": 2, "humidity": 67.14}, {"result": "True", "id": 3, "humidity": 69.58}, {"result": "True", "id": 4, "humidity": 74.57}, {"result": "True", "id": 5, "humidity": 68.53}, {"result": "True", "id": 6, "humidity": 72.32}]}}, {"timeAIR": "2023-01-23 18:23:32", "timeGROUND": "2023-01-23 18:23:32", "data": {"air": [{"result": "True", "id": 1, "temperature": 27.42, "humidity": 69.79}, {"result": "True", "id": 2, "temperature": 30.94, "humidity": 66.46}, {"result": "True", "id": 3, "temperature": 30.75, "humidity": 46.45}, {"result": "True", "id": 4, "temperature": 29.15, "humidity": 56.59}], "ground": [{"result": "True", "id": 1, "humidity": 65.52}, {"result": "True", "id": 2, "humidity": 70.22}, {"result": "True", "id": 3, "humidity": 71.18}, {"result": "True", "id": 4, "humidity": 70.0}, {"result": "True", "id": 5, "humidity": 66.8}, {"result": "True", "id": 6, "humidity": 72.37}]}}, {"timeAIR": "2023-01-23 18:23:36", "timeGROUND": "2023-01-23 18:23:37", "data": {"air": [{"result": "True", "id": 1, "temperature": 29.17, "humidity": 78.79}, {"result": "True", "id": 2, "temperature": 29.15, "humidity": 59.68}, {"result": "True", "id": 3, "temperature": 29.33, "humidity": 60.77}, {"result": "True", "id": 4, "temperature": 29.43, "humidity": 47.58}], "ground": [{"result": "True", "id": 1, "humidity": 65.35}, {"result": "True", "id": 2, "humidity": 71.61}, {"result": "True", "id": 3, "humidity": 68.44}, {"result": "True", "id": 4, "humidity": 71.44}, {"result": "True", "id": 5, "humidity": 74.31}, {"result": "True", "id": 6, "humidity": 66.02}]}}, {"timeAIR": "2023-01-23 18:23:41", "timeGROUND": "2023-01-23 18:23:41", "data": {"air": [{"result": "False", "id": 1}, {"result": "True", "id": 2, "temperature": 28.54, "humidity": 53.57}, {"result": "False", "id": 3}, {"result": "True", "id": 4, "temperature": 29.3, "humidity": 66.63}], "ground": [{"result": "False", "id": 1}, {"result": "False", "id": 2}, {"result": "True", "id": 3, "humidity": 65.11}, {"result": "True", "id": 4, "humidity": 65.86}, {"result": "False", "id": 5}, {"result": "False", "id": 6}]}}, {"timeAIR": "2023-01-23 18:23:46", "timeGROUND": "2023-01-23 18:23:47", "data": {"air": [{"result": "True", "id": 1, "temperature": 26.92, "humidity": 58.66}, {"result": "True", "id": 2, "temperature": 31.88, "humidity": 75.08}, {"result": "True", "id": 3, "temperature": 30.01, "humidity": 79.4}, {"result": "True", "id": 4, "temperature": 29.87, "humidity": 38.46}], "ground": [{"result": "False", "id": 1}, {"result": "False", "id": 2}, {"result": "False", "id": 3}, {"result": "True", "id": 4, "humidity": 70.66}, {"result": "False", "id": 5}, {"result": "False", "id": 6}]}}, {"timeAIR": "2023-01-23 18:23:52", "timeGROUND": "2023-01-23 18:23:53", "data": {"air": [{"result": "False", "id": 1}, {"result": "False", "id": 2}, {"result": "False", "id": 3}, {"result": "False", "id": 4}], "ground": [{"result": "False", "id": 1}, {"result": "False", "id": 2}, {"result": "False", "id": 3}, {"result": "True", "id": 4, "humidity": 69.4}, {"result": "False", "id": 5}, {"result": "True", "id": 6, "humidity": 70.89}]}}, {"timeAIR": "2023-01-23 18:23:58", "timeGROUND": "2023-01-23 18:23:58", "data": {"air": [{"result": "True", "id": 1, "temperature": 26.99, "humidity": 76.24}, {"result": "True", "id": 2, "temperature": 30.23, "humidity": 55.73}, {"result": "True", "id": 3, "temperature": 28.97, "humidity": 79.75}, {"result": "True", "id": 4, "temperature": 29.44, "humidity": 70.31}], "ground": [{"result": "True", "id": 1, "humidity": 67.5}, {"result": "True", "id": 2, "humidity": 62.85}, {"result": "True", "id": 3, "humidity": 72.3}, {"result": "True", "id": 4, "humidity": 69.4}, {"result": "True", "id": 5, "humidity": 73.6}, {"result": "True", "id": 6, "humidity": 66.01}]}}, {"timeAIR": "2023-01-23 18:24:02", "timeGROUND": "2023-01-23 18:24:02", "data": {"air": [{"result": "True", "id": 1, "temperature": 32.82, "humidity": 47.5}, {"result": "True", "id": 2, "temperature": 29.7, "humidity": 58.78}, {"result": "True", "id": 3, "temperature": 28.53, "humidity": 63.5}, {"result": "True", "id": 4, "temperature": 29.88, "humidity": 75.51}], "ground": [{"result": "True", "id": 1, "humidity": 61.97}, {"result": "False", "id": 2}, {"result": "True", "id": 3, "humidity": 74.06}, {"result": "True", "id": 4, "humidity": 73.53}, {"result": "False", "id": 5}, {"result": "False", "id": 6}]}}, {"timeAIR": "2023-01-23 18:24:07", "timeGROUND": "2023-01-23 18:24:07", "data": {"air": [{"result": "True", "id": 1, "temperature": 29.38, "humidity": 61.25}, {"result": "True", "id": 2, "temperature": 29.39, "humidity": 44.67}, {"result": "True", "id": 3, "temperature": 30.33, "humidity": 56.24}, {"result": "True", "id": 4, "temperature": 29.8, "humidity": 60.47}], "ground": [{"result": "True", "id": 1, "humidity": 68.32}, {"result": "False", "id": 2}, {"result": "False", "id": 3}, {"result": "True", "id": 4, "humidity": 74.37}, {"result": "True", "id": 5, "humidity": 68.13}, {"result": "False", "id": 6}]}}, {"timeAIR": "2023-01-23 18:24:11", "timeGROUND": "2023-01-23 18:24:11", "data": {"air": [{"result": "True", "id": 1, "temperature": 26.04, "humidity": 40.9}, {"result": "True", "id": 2, "temperature": 29.79, "humidity": 42.47}, {"result": "True", "id": 3, "temperature": 30.22, "humidity": 44.06}, {"result": "True", "id": 4, "temperature": 29.08, "humidity": 72.78}], "ground": [{"result": "True", "id": 1, "humidity": 77.12}, {"result": "True", "id": 2, "humidity": 66.43}, {"result": "True", "id": 3, "humidity": 64.03}, {"result": "True", "id": 4, "humidity": 69.64}, {"result": "True", "id": 5, "humidity": 73.74}, {"result": "True", "id": 6, "humidity": 67.1}]}}, {"timeAIR": "2023-01-23 18:24:16", "timeGROUND": "2023-01-23 18:24:16", "data": {"air": [{"result": "True", "id": 1, "temperature": 27.62, "humidity": 66.44}, {"result": "False", "id": 2}, {"result": "True", "id": 3, "temperature": 30.23, "humidity": 43.68}, {"result": "True", "id": 4, "temperature": 29.11, "humidity": 39.97}], "ground": [{"result": "True", "id": 1, "humidity": 65.75}, {"result": "True", "id": 2, "humidity": 71.57}, {"result": "True", "id": 3, "humidity": 70.06}, {"result": "True", "id": 4, "humidity": 74.85}, {"result": "True", "id": 5, "humidity": 71.83}, {"result": "True", "id": 6, "humidity": 73.02}]}}, {"timeAIR": "2023-01-23 18:24:20", "timeGROUND": "2023-01-23 18:24:21", "data": {"air": [{"result": "True", "id": 1, "temperature": 28.49, "humidity": 59.78}, {"result": "True", "id": 2, "temperature": 31.75, "humidity": 49.48}, {"result": "True", "id": 3, "temperature": 28.5, "humidity": 59.88}, {"result": "True", "id": 4, "temperature": 29.48, "humidity": 51.94}], "ground": [{"result": "True", "id": 1, "humidity": 67.37}, {"result": "True", "id": 2, "humidity": 71.71}, {"result": "True", "id": 3, "humidity": 76.23}, {"result": "True", "id": 4, "humidity": 67.41}, {"result": "True", "id": 5, "humidity": 67.98}, {"result": "True", "id": 6, "humidity": 70.04}]}}, {"timeAIR": "2023-01-23 18:24:25", "timeGROUND": "2023-01-23 18:24:25", "data": {"air": [{"result": "True", "id": 1, "temperature": 30.07, "humidity": 56.98}, {"result": "True", "id": 2, "temperature": 29.23, "humidity": 43.24}, {"result": "True", "id": 3, "temperature": 28.15, "humidity": 40.32}, {"result": "True", "id": 4, "temperature": 29.43, "humidity": 55.64}], "ground": [{"result": "True", "id": 1, "humidity": 63.25}, {"result": "True", "id": 2, "humidity": 76.73}, {"result": "True", "id": 3, "humidity": 64.34}, {"result": "False", "id": 4}, {"result": "False", "id": 5}, {"result": "True", "id": 6, "humidity": 68.6}]}}, {"timeAIR": "2023-01-23 18:24:30", "timeGROUND": "2023-01-23 18:24:30", "data": {"air": [{"result": "True", "id": 1, "temperature": 26.96, "humidity": 46.77}, {"result": "False", "id": 2}, {"result": "False", "id": 3}, {"result": "False", "id": 4}], "ground": [{"result": "False", "id": 1}, {"result": "True", "id": 2, "humidity": 77.98}, {"result": "True", "id": 3, "humidity": 65.28}, {"result": "True", "id": 4, "humidity": 68.2}, {"result": "True", "id": 5, "humidity": 65.81}, {"result": "True", "id": 6, "humidity": 72.54}]}}, {"timeAIR": "2023-01-23 18:24:34", "timeGROUND": "2023-01-23 18:24:34", "data": {"air": [{"result": "True", "id": 1, "temperature": 31.37, "humidity": 58.88}, {"result": "True", "id": 2, "temperature": 31.03, "humidity": 58.61}, {"result": "True", "id": 3, "temperature": 29.57, "humidity": 52.96}, {"result": "True", "id": 4, "temperature": 29.98, "humidity": 36.62}], "ground": [{"result": "True", "id": 1, "humidity": 74.8}, {"result": "True", "id": 2, "humidity": 64.64}, {"result": "True", "id": 3, "humidity": 66.11}, {"result": "True", "id": 4, "humidity": 64.71}, {"result": "True", "id": 5, "humidity": 68.13}, {"result": "True", "id": 6, "humidity": 72.37}]}}, {"timeAIR": "2023-01-23 18:24:39", "timeGROUND": "2023-01-23 18:24:39", "data": {"air": [{"result": "True", "id": 1, "temperature": 30.06, "humidity": 49.17}, {"result": "True", "id": 2, "temperature": 31.9, "humidity": 72.93}, {"result": "True", "id": 3, "temperature": 29.93, "humidity": 37.86}, {"result": "True", "id": 4, "temperature": 29.52, "humidity": 48.78}], "ground": [{"result": "True", "id": 1, "humidity": 67.91}, {"result": "True", "id": 2, "humidity": 74.76}, {"result": "False", "id": 3}, {"result": "True", "id": 4, "humidity": 67.59}, {"result": "True", "id": 5, "humidity": 68.84}, {"result": "True", "id": 6, "humidity": 73.22}]}}, {"timeAIR": "2023-01-23 18:24:43", "timeGROUND": "2023-01-23 18:24:43", "data": {"air": [{"result": "True", "id": 1, "temperature": 28.34, "humidity": 48.0}, {"result": "True", "id": 2, "temperature": 29.43, "humidity": 39.32}, {"result": "True", "id": 3, "temperature": 29.09, "humidity": 64.07}, {"result": "True", "id": 4, "temperature": 29.04, "humidity": 46.59}], "ground": [{"result": "True", "id": 1, "humidity": 62.32}, {"result": "True", "id": 2, "humidity": 73.88}, {"result": "True", "id": 3, "humidity": 65.17}, {"result": "True", "id": 4, "humidity": 75.29}, {"result": "True", "id": 5, "humidity": 68.99}, {"result": "True", "id": 6, "humidity": 73.59}]}}, {"timeAIR": "2023-01-23 18:24:48", "timeGROUND": "2023-01-23 18:24:48", "data": {"air": [{"result": "True", "id": 1, "temperature": 28.76, "humidity": 75.65}, {"result": "True", "id": 2, "temperature": 27.7, "humidity": 49.29}, {"result": "True", "id": 3, "temperature": 28.58, "humidity": 68.49}, {"result": "True", "id": 4, "temperature": 29.06, "humidity": 73.46}], "ground": [{"result": "True", "id": 1, "humidity": 69.18}, {"result": "True", "id": 2, "humidity": 62.1}, {"result": "True", "id": 3, "humidity": 65.23}, {"result": "True", "id": 4, "humidity": 72.17}, {"result": "True", "id": 5, "humidity": 69.84}, {"result": "True", "id": 6, "humidity": 68.3}]}}, {"timeAIR": "2023-01-23 18:24:52", "timeGROUND": "2023-01-23 18:24:53", "data": {"air": [{"result": "True", "id": 1, "temperature": 31.06, "humidity": 53.26}, {"result": "True", "id": 2, "temperature": 28.24, "humidity": 48.8}, {"result": "True", "id": 3, "temperature": 29.84, "humidity": 70.99}, {"result": "True", "id": 4, "temperature": 29.69, "humidity": 57.26}], "ground": [{"result": "True", "id": 1, "humidity": 69.57}, {"result": "True", "id": 2, "humidity": 65.78}, {"result": "True", "id": 3, "humidity": 67.8}, {"result": "True", "id": 4, "humidity": 75.12}, {"result": "False", "id": 5}, {"result": "True", "id": 6, "humidity": 68.81}]}}, {"timeAIR": "2023-01-23 18:24:57", "timeGROUND": "2023-01-23 18:24:57", "data": {"air": [{"result": "False", "id": 1}, {"result": "True", "id": 2, "temperature": 28.52, "humidity": 50.3}, {"result": "True", "id": 3, "temperature": 29.56, "humidity": 82.17}, {"result": "True", "id": 4, "temperature": 29.82, "humidity": 59.89}], "ground": [{"result": "True", "id": 1, "humidity": 73.6}, {"result": "True", "id": 2, "humidity": 69.5}, {"result": "False", "id": 3}, {"result": "True", "id": 4, "humidity": 64.05}, {"result": "True", "id": 5, "humidity": 71.66}, {"result": "True", "id": 6, "humidity": 70.95}]}}, {"timeAIR": "2023-01-23 18:25:01", "timeGROUND": "2023-01-23 18:25:02", "data": {"air": [{"result": "True", "id": 1, "temperature": 31.0, "humidity": 77.24}, {"result": "True", "id": 2, "temperature": 31.59, "humidity": 40.85}, {"result": "True", "id": 3, "temperature": 28.65, "humidity": 74.35}, {"result": "True", "id": 4, "temperature": 29.19, "humidity": 76.65}], "ground": [{"result": "True", "id": 1, "humidity": 77.34}, {"result": "True", "id": 2, "humidity": 64.36}, {"result": "True", "id": 3, "humidity": 76.65}, {"result": "True", "id": 4, "humidity": 74.91}, {"result": "True", "id": 5, "humidity": 73.54}, {"result": "True", "id": 6, "humidity": 66.87}]}}, {"timeAIR": "2023-01-23 18:25:06", "timeGROUND": "2023-01-23 18:25:06", "data": {"air": [{"result": "True", "id": 1, "temperature": 29.29, "humidity": 71.97}, {"result": "False", "id": 2}, {"result": "False", "id": 3}, {"result": "False", "id": 4}], "ground": [{"result": "True", "id": 1, "humidity": 67.09}, {"result": "False", "id": 2}, {"result": "True", "id": 3, "humidity": 76.44}, {"result": "True", "id": 4, "humidity": 64.35}, {"result": "True", "id": 5, "humidity": 67.41}, {"result": "True", "id": 6, "humidity": 68.89}]}}, {"timeAIR": "2023-01-23 18:25:10", "timeGROUND": "2023-01-23 18:25:11", "data": {"air": [{"result": "True", "id": 1, "temperature": 28.95, "humidity": 71.93}, {"result": "False", "id": 2}, {"result": "True", "id": 3, "temperature": 29.79, "humidity": 44.97}, {"result": "True", "id": 4, "temperature": 29.62, "humidity": 58.95}], "ground": [{"result": "True", "id": 1, "humidity": 74.26}, {"result": "True", "id": 2, "humidity": 71.04}, {"result": "True", "id": 3, "humidity": 72.33}, {"result": "True", "id": 4, "humidity": 75.52}, {"result": "True", "id": 5, "humidity": 66.64}, {"result": "True", "id": 6, "humidity": 67.03}]}}
  ]},
  "options": {
    "temperature": 30,
    "AIRhumidity": 60,
    "GROUNDhumidity": 70
  },
  "incorrect_params": {
    "message": "   !"
  },
  "cant_off_sistem": {
    "message": "     !"
  },
  "all_correct": {
    "message": "  !"
  },





  "Records": {
  "ok": true,
  "result": {
    "air": [
      [1, 21.1, 53.87, 1673777900],
      [2, 22.1, 63.87, 1673777900],
      [3, 23.1, 43.87, 1673777900],
      [1, 22.2, 79.87, 1673777905],
      [2, 23.2, 79.87, 1673777905],
      [3, 24.2, 79.87, 1673777905],
      [1, 23.3, 47.00, 1673777910],
      [2, 24.3, 47.00, 1673777910],
      [3, 25.3, 47.00, 1673777910]
    ],
    "ground": [
      [1, 41.1, 1673777900],
      [2, 42.2, 1673777900],
      [1, 43.3, 1673777905],
      [2, 52.87, 1673777905],
      [1, 61.87, 1673777910],
      [2, 72.87, 1673777910]
    ]
  }
  },
  
 
  "Test1": {
    "Header": "   HTML  JavaScript   Fetch      JSON",
    "Data": [
{"label": "2023-01-10 13:00:00", "value":87.7821},
{"label": "2023-01-10 13:00:05", "value":92.6052},
{"label": "2023-01-10 13:00:10", "value":60.8511},
{"label": "2023-01-10 13:00:15", "value":17.2366},
{"label": "2023-01-10 13:00:20", "value":79.7812},
{"label": "2023-01-10 13:00:25", "value":25.5406},
{"label": "2023-01-10 13:00:30", "value":17.6256},
{"label": "2023-01-10 13:00:35", "value":92.1629},
{"label": "2023-01-10 13:00:40", "value":46.4648},
{"label": "2023-01-10 13:00:45", "value":13.3708},
{"label": "2023-01-10 13:00:50", "value":41.847},
{"label": "2023-01-10 13:00:55", "value":63.2864},
{"label": "2023-01-10 13:01:00", "value":97.2695},
{"label": "2023-01-10 13:01:05", "value":91.1872},
{"label": "2023-01-10 13:01:10", "value":55.7295},
{"label": "2023-01-10 13:01:15", "value":96.4409},
{"label": "2023-01-10 13:01:20", "value":0.0257},
{"label": "2023-01-10 13:01:25", "value":33.743},
{"label": "2023-01-10 13:01:30", "value":80.8095},
{"label": "2023-01-10 13:01:35", "value":61.2792},
{"label": "2023-01-10 13:01:40", "value":42.5979},
{"label": "2023-01-10 13:01:45", "value":78.5382},
{"label": "2023-01-10 13:01:50", "value":79.6647},
{"label": "2023-01-10 13:01:55", "value":86.8699},
{"label": "2023-01-10 13:02:00", "value":10.2106},
{"label": "2023-01-10 13:02:05", "value":19.2851},
{"label": "2023-01-10 13:02:10", "value":15.4265},
{"label": "2023-01-10 13:02:15", "value":86.0667},
{"label": "2023-01-10 13:02:20", "value":31.8831},
{"label": "2023-01-10 13:02:25", "value":54.3609},
{"label": "2023-01-10 13:02:30", "value":10.377},
{"label": "2023-01-10 13:02:35", "value":64.3547},
{"label": "2023-01-10 13:02:40", "value":52.6903},
{"label": "2023-01-10 13:02:45", "value":10.9573},
{"label": "2023-01-10 13:02:50", "value":18.3697},
{"label": "2023-01-10 13:02:55", "value":15.552},
{"label": "2023-01-10 13:03:00", "value":24.2672},
{"label": "2023-01-10 13:03:05", "value":37.2929},
{"label": "2023-01-10 13:03:10", "value":91.7419},
{"label": "2023-01-10 13:03:15", "value":74.8389},
{"label": "2023-01-10 13:03:20", "value":32.9165},
{"label": "2023-01-10 13:03:25", "value":16.9536},
{"label": "2023-01-10 13:03:30", "value":99.1639},
{"label": "2023-01-10 13:03:35", "value":83.3422},
{"label": "2023-01-10 13:03:40", "value":19.1679},
{"label": "2023-01-10 13:03:45", "value":41.2734},
{"label": "2023-01-10 13:03:50", "value":10.851},
{"label": "2023-01-10 13:03:55", "value":69.2517},
{"label": "2023-01-10 13:04:00", "value":45.3902},
{"label": "2023-01-10 13:04:05", "value":32.9689},
{"label": "2023-01-10 13:04:10", "value":23.0357},
{"label": "2023-01-10 13:04:15", "value":64.5457},
{"label": "2023-01-10 13:04:20", "value":26.3609},
{"label": "2023-01-10 13:04:25", "value":97.5718},
{"label": "2023-01-10 13:04:30", "value":31.6906},
{"label": "2023-01-10 13:04:35", "value":59.1942},
{"label": "2023-01-10 13:04:40", "value":43.6986},
{"label": "2023-01-10 13:04:45", "value":87.0669},
{"label": "2023-01-10 13:04:50", "value":5.9706},
{"label": "2023-01-10 13:04:55", "value":38.1291},
{"label": "2023-01-10 13:05:00", "value":42.9802},
{"label": "2023-01-10 13:05:05", "value":21.1515},
{"label": "2023-01-10 13:05:10", "value":50.4863},
{"label": "2023-01-10 13:05:15", "value":19.4183},
{"label": "2023-01-10 13:05:20", "value":39.932},
{"label": "2023-01-10 13:05:25", "value":88.6162},
{"label": "2023-01-10 13:05:30", "value":18.248},
{"label": "2023-01-10 13:05:35", "value":33.0865},
{"label": "2023-01-10 13:05:40", "value":22.2425},
{"label": "2023-01-10 13:05:45", "value":70.9032},
{"label": "2023-01-10 13:05:50", "value":43.2014},
{"label": "2023-01-10 13:05:55", "value":38.8279},
{"label": "2023-01-10 13:06:00", "value":97.3377},
{"label": "2023-01-10 13:06:05", "value":8.7444},
{"label": "2023-01-10 13:06:10", "value":4.2487},
{"label": "2023-01-10 13:06:15", "value":85.665},
{"label": "2023-01-10 13:06:20", "value":44.4498},
{"label": "2023-01-10 13:06:25", "value":19.3111},
{"label": "2023-01-10 13:06:30", "value":45.4716},
{"label": "2023-01-10 13:06:35", "value":80.3792},
{"label": "2023-01-10 13:06:40", "value":16.4787},
{"label": "2023-01-10 13:06:45", "value":29.3856},
{"label": "2023-01-10 13:06:50", "value":27.0524},
{"label": "2023-01-10 13:06:55", "value":53.7458},
{"label": "2023-01-10 13:07:00", "value":95.7758},
{"label": "2023-01-10 13:07:05", "value":59.2168},
{"label": "2023-01-10 13:07:10", "value":25.5809},
{"label": "2023-01-10 13:07:15", "value":3.086},
{"label": "2023-01-10 13:07:20", "value":98.6157},
{"label": "2023-01-10 13:07:25", "value":1.8355},
{"label": "2023-01-10 13:07:30", "value":78.3393},
{"label": "2023-01-10 13:07:35", "value":45.789},
{"label": "2023-01-10 13:07:40", "value":81.6026},
{"label": "2023-01-10 13:07:45", "value":25.4388},
{"label": "2023-01-10 13:07:50", "value":38.6381},
{"label": "2023-01-10 13:07:55", "value":66.3941},
{"label": "2023-01-10 13:08:00", "value":50.7905},
{"label": "2023-01-10 13:08:05", "value":1.587},
{"label": "2023-01-10 13:08:10", "value":98.8948},
{"label": "2023-01-10 13:08:15", "value":37.1377},
{"label": "2023-01-10 13:08:20", "value":50.6128},
{"label": "2023-01-10 13:08:25", "value":53.5},
{"label": "2023-01-10 13:08:30", "value":13.9064},
{"label": "2023-01-10 13:08:35", "value":46.3559},
{"label": "2023-01-10 13:08:40", "value":57.0296},
{"label": "2023-01-10 13:08:45", "value":58.9711},
{"label": "2023-01-10 13:08:50", "value":82.3786},
{"label": "2023-01-10 13:08:55", "value":25.2161},
{"label": "2023-01-10 13:09:00", "value":27.4253},
{"label": "2023-01-10 13:09:05", "value":98.2505},
{"label": "2023-01-10 13:09:10", "value":52.8775},
{"label": "2023-01-10 13:09:15", "value":73.4372},
{"label": "2023-01-10 13:09:20", "value":6.4607},
{"label": "2023-01-10 13:09:25", "value":31.6027},
{"label": "2023-01-10 13:09:30", "value":28.5426},
{"label": "2023-01-10 13:09:35", "value":29.5191},
{"label": "2023-01-10 13:09:40", "value":69.4433},
{"label": "2023-01-10 13:09:45", "value":55.1402},
{"label": "2023-01-10 13:09:50", "value":19.9713},
{"label": "2023-01-10 13:09:55", "value":55.9065},
{"label": "2023-01-10 13:10:00", "value":86.7788},
{"label": "2023-01-10 13:10:05", "value":12.8077},
{"label": "2023-01-10 13:10:10", "value":67.0168},
{"label": "2023-01-10 13:10:15", "value":67.1325},
{"label": "2023-01-10 13:10:20", "value":95.9542},
{"label": "2023-01-10 13:10:25", "value":56.7568},
{"label": "2023-01-10 13:10:30", "value":52.1309},
{"label": "2023-01-10 13:10:35", "value":78.5621},
{"label": "2023-01-10 13:10:40", "value":14.4275},
{"label": "2023-01-10 13:10:45", "value":75.0916},
{"label": "2023-01-10 13:10:50", "value":61.3273},
{"label": "2023-01-10 13:10:55", "value":76.6305},
{"label": "2023-01-10 13:11:00", "value":0.3142},
{"label": "2023-01-10 13:11:05", "value":61.8746},
{"label": "2023-01-10 13:11:10", "value":45.4659},
{"label": "2023-01-10 13:11:15", "value":68.4482},
{"label": "2023-01-10 13:11:20", "value":14.0769},
{"label": "2023-01-10 13:11:25", "value":10.8398},
{"label": "2023-01-10 13:11:30", "value":61.9119},
{"label": "2023-01-10 13:11:35", "value":68.6799},
{"label": "2023-01-10 13:11:40", "value":64.1303},
{"label": "2023-01-10 13:11:45", "value":34.0601},
{"label": "2023-01-10 13:11:50", "value":10.3911},
{"label": "2023-01-10 13:11:55", "value":30.1223},
{"label": "2023-01-10 13:12:00", "value":12.5439},
{"label": "2023-01-10 13:12:05", "value":94.0156},
{"label": "2023-01-10 13:12:10", "value":93.7778},
{"label": "2023-01-10 13:12:15", "value":18.35},
{"label": "2023-01-10 13:12:20", "value":29.1281},
{"label": "2023-01-10 13:12:25", "value":2.6625},
{"label": "2023-01-10 13:12:30", "value":21.0954},
{"label": "2023-01-10 13:12:35", "value":92.9896},
{"label": "2023-01-10 13:12:40", "value":94.9149},
{"label": "2023-01-10 13:12:45", "value":26.6105},
{"label": "2023-01-10 13:12:50", "value":72.8898},
{"label": "2023-01-10 13:12:55", "value":81.3133},
{"label": "2023-01-10 13:13:00", "value":13.6098},
{"label": "2023-01-10 13:13:05", "value":74.198},
{"label": "2023-01-10 13:13:10", "value":72.0648}
    ]
  }
}
